proj2_make/TOP/1_RTL/baud_gen.v
`timescale 1ns / 1ps 

module baud_gen (
		clk			,
		nRst		,
		i_ibrd		,
		o_tick_16x
);

input			clk			;
input			nRst		;
input	[15:0]	i_ibrd		;
output			o_tick_16x	;

reg		[15:0]	r_count		;

always @( posedge clk or negedge nRst )begin
	if	(!nRst) 
		r_count <= 16'd0			;
	else if	(i_ibrd == 16'd0) 
		r_count <= 16'd0			;
	else if (r_count >= i_ibrd-1) 
		r_count <= 16'd0			;
	else		
		r_count <= r_count + 1		; 	 
end		

assign o_tick_16x = (i_ibrd != 16'd0)&&(r_count == i_ibrd-1)	;

endmodule

proj2_make/TOP/2_SIM/TESTBENCH/tb_baud_gen.v
//==============================================================================
// Testbench : tb_baud_gen
// DUT       : baud_gen
// Checks    : (0) reset            -> tick is 0 while nRst is low
//             (1) IBRD = 0         -> no tick
//             (2) IBRD = N         -> N ticks per (N * M) clocks
//             (3) IBRD = N         -> tick spacing is N clocks, 1 clock wide
//             (4) reset in middle  -> counter restarts from 0
//             (5) IBRD change      -> new period is used, counter does not hang
//             (6) IBRD -> 0        -> tick stops
// Result    : prints PASS / FAIL per item and the number of errors at the end
//==============================================================================

`timescale 1ns / 1ps

module tb_baud_gen;

//------------------------------------------------------------------------------
// DUT signals
//------------------------------------------------------------------------------
reg             clk         ;
reg             nRst        ;
reg     [15:0]  i_ibrd      ;
wire            o_tick_16x  ;

integer         err_cnt     ;   // number of failed checks
integer         r_cyc       ;   // free-running clock counter (to measure spacing)

//------------------------------------------------------------------------------
// DUT
//------------------------------------------------------------------------------
baud_gen    uut (
                .clk        (clk        )   ,
                .nRst       (nRst       )   ,
                .i_ibrd     (i_ibrd     )   ,
                .o_tick_16x (o_tick_16x )
);

//------------------------------------------------------------------------------
// Clock : 100 MHz
//------------------------------------------------------------------------------
initial clk = 1'b0;
always  #5 clk = ~clk;

initial r_cyc = 0;
always @(posedge clk) r_cyc <= r_cyc + 1;

//------------------------------------------------------------------------------
// Tasks
//------------------------------------------------------------------------------
// Hold reset for 3 clocks, release just after a clock edge
task do_reset;
begin
    nRst = 1'b0;
    repeat (3) @(posedge clk);
    #1 nRst = 1'b1;
end
endtask

// Wait n clock edges. The sample point is 1 ns after the edge, so the DUT
// outputs are stable and there is no race with the clock.
task wait_clk(input integer n);
begin
    repeat (n) @(posedge clk);
    #1;
end
endtask

// Count the ticks in a window of clocks and compare with the expected number
task check_tick_count(input [15:0] ibrd, input integer window, input integer expected);
    integer k;
    integer ticks;
begin
    i_ibrd = ibrd;
    do_reset;
    ticks = 0;
    for (k = 0; k < window; k = k + 1) begin
        wait_clk(1);
        if (o_tick_16x === 1'b1) ticks = ticks + 1;
    end
    if (ticks !== expected) begin
        $display("[FAIL] IBRD=%0d : %0d ticks in %0d clk (exp %0d)",
                  ibrd, ticks, window, expected);
        err_cnt = err_cnt + 1;
    end
    else
        $display("[PASS] IBRD=%0d : %0d ticks in %0d clk", ibrd, ticks, window);
end
endtask

// Check n_ticks consecutive ticks:
//   - spacing between two ticks is exactly IBRD clocks
//   - the tick is high for 1 clock only (IBRD = 1 : high on every clock)
task check_period(input [15:0] ibrd, input integer n_ticks);
    integer k;
    integer last;
    integer errs_before;
begin
    errs_before = err_cnt;
    i_ibrd = ibrd;
    do_reset;
    last = -1;
    k    = 0;
    while (k < n_ticks) begin
        wait_clk(1);
        if (o_tick_16x === 1'b1) begin
            if (last >= 0 && (r_cyc - last) != ibrd) begin
                $display("[FAIL] IBRD=%0d : tick spacing %0d clk (exp %0d)",
                          ibrd, r_cyc - last, ibrd);
                err_cnt = err_cnt + 1;
            end
            last = r_cyc;
            k    = k + 1;
            if (ibrd != 16'd1) begin
                wait_clk(1);
                if (o_tick_16x !== 1'b0) begin
                    $display("[FAIL] IBRD=%0d : tick wider than 1 clock", ibrd);
                    err_cnt = err_cnt + 1;
                end
            end
        end
        else if (last >= 0 && (r_cyc - last) > ibrd) begin
            $display("[FAIL] IBRD=%0d : tick missing", ibrd);
            err_cnt = err_cnt + 1;
            k = n_ticks;
        end
    end
    if (err_cnt == errs_before)
        $display("[PASS] IBRD=%0d : %0d ticks, spacing and width ok", ibrd, n_ticks);
end
endtask

//------------------------------------------------------------------------------
// Main sequence
//------------------------------------------------------------------------------
integer k;
integer t;

initial begin
    err_cnt = 0;
    nRst    = 1'b0;
    i_ibrd  = 16'd0;
    #1;

    // (0) tick must be 0 while reset is asserted
    wait_clk(3);
    if (o_tick_16x !== 1'b0) begin
        $display("[FAIL] tick must be 0 during reset");
        err_cnt = err_cnt + 1;
    end
    else
        $display("[PASS] tick is 0 during reset");

    // (1) IBRD = 0 : divider disabled
    nRst = 1'b1;
    wait_clk(50);
    if (o_tick_16x !== 1'b0) begin
        $display("[FAIL] IBRD=0 : tick must stay 0");
        err_cnt = err_cnt + 1;
    end
    else
        $display("[PASS] IBRD=0 : no tick");

    // (2) number of ticks in a fixed window
    check_tick_count(16'd1,  100, 100);     // every clock
    check_tick_count(16'd2,  100,  50);
    check_tick_count(16'd10, 100,  10);
    check_tick_count(16'd27, 270,  10);     // odd value

    // (3) tick spacing and pulse width
    check_period(16'd2,   5);
    check_period(16'd5,   5);
    check_period(16'd16,  5);
    check_period(16'd163, 3);               // 50 MHz / (16 * 19200) style value

    // (4) reset in the middle of a count : restart from 0
    i_ibrd = 16'd20;
    do_reset;
    wait_clk(10);                           // counter is in the middle
    nRst = 1'b0;
    wait_clk(2);
    if (o_tick_16x !== 1'b0) begin
        $display("[FAIL] tick must be 0 while reset is asserted");
        err_cnt = err_cnt + 1;
    end
    #1 nRst = 1'b1;
    // first tick comes (IBRD-1) clocks after release (count 0 -> IBRD-1)
    for (k = 1; k < 19; k = k + 1) begin
        wait_clk(1);
        if (o_tick_16x === 1'b1) begin
            $display("[FAIL] early tick after reset (clk %0d)", k);
            err_cnt = err_cnt + 1;
        end
    end
    wait_clk(1);
    if (o_tick_16x !== 1'b1) begin
        $display("[FAIL] tick missing 19 clk after reset");
        err_cnt = err_cnt + 1;
    end
    else
        $display("[PASS] reset restarts the counter");

    // (5) IBRD changed on the fly (large -> small) : counter must not hang
    i_ibrd = 16'd50;
    do_reset;
    wait_clk(30);                           // counter is above the new IBRD-1
    i_ibrd = 16'd5;
    wait_clk(7);                            // a tick shows up within IBRD clocks
    t = 0;
    for (k = 0; k < 20; k = k + 1) begin
        wait_clk(1);
        if (o_tick_16x === 1'b1) t = t + 1;
    end
    if (t !== 4) begin
        $display("[FAIL] IBRD 50->5 : %0d ticks in 20 clk (exp 4)", t);
        err_cnt = err_cnt + 1;
    end
    else
        $display("[PASS] IBRD changed on the fly");

    // (6) IBRD -> 0 while running : tick stops
    i_ibrd = 16'd0;
    wait_clk(2);
    t = 0;
    for (k = 0; k < 30; k = k + 1) begin
        wait_clk(1);
        if (o_tick_16x !== 1'b0) t = t + 1;
    end
    if (t != 0) begin
        $display("[FAIL] IBRD=0 : %0d ticks after IBRD set to 0", t);
        err_cnt = err_cnt + 1;
    end
    else
        $display("[PASS] IBRD set to 0 : tick stops");

    //--------------------------------------------------------------------------
    if (err_cnt == 0) $display("=== tb_baud_gen : ALL PASS ===");
    else              $display("=== tb_baud_gen : FAIL (%0d errors) ===", err_cnt);
    $finish;
end

//------------------------------------------------------------------------------
// Waveform dump + watchdog
//------------------------------------------------------------------------------
initial begin
    $dumpfile("./DUMP/tb_baud_gen.vcd");
    $dumpvars(0, tb_baud_gen);
end

initial begin
    #200000;
    $display("[FAIL] timeout");
    $finish;
end

endmodule

proj2_make/TOP/2_SIM/FUNCTION/DUMP/tb_baud_gen.vcd
$date
    Oct  8, 2026  15:20:57
$end
$version
    TOOL:	xmsim(64)	22.03-s012
$end
$timescale
    1 ps
$end

$scope module tb_baud_gen $end
$var reg       1 !    clk $end
$var reg       1 "    nRst $end
$var reg      16 #    i_ibrd [15:0] $end
$var wire      1 $    o_tick_16x  $end
$var integer  32 %    err_cnt $end
$var integer  32 &    r_cyc $end
$var integer  32 '    k $end
$var integer  32 (    t $end

$scope module uut $end
$var wire      1 )    clk  $end
$var wire      1 *    nRst  $end
$var wire     16 +    i_ibrd [15:0] $end
$var wire      1 $    o_tick_16x  $end
$var reg      16 ,    r_count [15:0] $end
$upscope $end


$scope task wait_clk $end
$var integer  32 -    n $end
$upscope $end


$scope task check_tick_count $end
$var reg      16 .    ibrd [15:0] $end
$var integer  32 /    window $end
$var integer  32 0    expected $end
$var integer  32 1    k $end
$var integer  32 2    ticks $end
$upscope $end


$scope task check_period $end
$var reg      16 3    ibrd [15:0] $end
$var integer  32 4    n_ticks $end
$var integer  32 5    k $end
$var integer  32 6    last $end
$var integer  32 7    errs_before $end
$upscope $end

$upscope $end

$enddefinitions $end
$dumpvars
0!
0"
b0 #
0$
b0 %
b0 &
bx '
bx (
0)
0*
b0 +
b0 ,
bx -
bx .
bx /
bx 0
bx 1
bx 2
bx 3
bx 4
bx 5
bx 6
bx 7
$end
#1000
b11 -
#5000
1!
1)
b1 &
#10000
0!
0)
#15000
1!
1)
b10 &
#20000
0!
0)
#25000
1!
1)
b11 &
#26000
1"
b110010 -
1*
#30000
0!
0)
#35000
1!
1)
b100 &
#40000
0!
0)
#45000
1!
1)
b101 &
#50000
0!
0)
#55000
1!
1)
b110 &
#60000
0!
0)
#65000
1!
1)
b111 &
#70000
0!
0)
#75000
1!
1)
b1000 &
#80000
0!
0)
#85000
1!
1)
b1001 &
#90000
0!
0)
#95000
1!
1)
b1010 &
#100000
0!
0)
#105000
1!
1)
b1011 &
#110000
0!
0)
#115000
1!
1)
b1100 &
#120000
0!
0)
#125000
1!
1)
b1101 &
#130000
0!
0)
#135000
1!
1)
b1110 &
#140000
0!
0)
#145000
1!
1)
b1111 &
#150000
0!
0)
#155000
1!
1)
b10000 &
#160000
0!
0)
#165000
1!
1)
b10001 &
#170000
0!
0)
#175000
1!
1)
b10010 &
#180000
0!
0)
#185000
1!
1)
b10011 &
#190000
0!
0)
#195000
1!
1)
b10100 &
#200000
0!
0)
#205000
1!
1)
b10101 &
#210000
0!
0)
#215000
1!
1)
b10110 &
#220000
0!
0)
#225000
1!
1)
b10111 &
#230000
0!
0)
#235000
1!
1)
b11000 &
#240000
0!
0)
#245000
1!
1)
b11001 &
#250000
0!
0)
#255000
1!
1)
b11010 &
#260000
0!
0)
#265000
1!
1)
b11011 &
#270000
0!
0)
#275000
1!
1)
b11100 &
#280000
0!
0)
#285000
1!
1)
b11101 &
#290000
0!
0)
#295000
1!
1)
b11110 &
#300000
0!
0)
#305000
1!
1)
b11111 &
#310000
0!
0)
#315000
1!
1)
b100000 &
#320000
0!
0)
#325000
1!
1)
b100001 &
#330000
0!
0)
#335000
1!
1)
b100010 &
#340000
0!
0)
#345000
1!
1)
b100011 &
#350000
0!
0)
#355000
1!
1)
b100100 &
#360000
0!
0)
#365000
1!
1)
b100101 &
#370000
0!
0)
#375000
1!
1)
b100110 &
#380000
0!
0)
#385000
1!
1)
b100111 &
#390000
0!
0)
#395000
1!
1)
b101000 &
#400000
0!
0)
#405000
1!
1)
b101001 &
#410000
0!
0)
#415000
1!
1)
b101010 &
#420000
0!
0)
#425000
1!
1)
b101011 &
#430000
0!
0)
#435000
1!
1)
b101100 &
#440000
0!
0)
#445000
1!
1)
b101101 &
#450000
0!
0)
#455000
1!
1)
b101110 &
#460000
0!
0)
#465000
1!
1)
b101111 &
#470000
0!
0)
#475000
1!
1)
b110000 &
#480000
0!
0)
#485000
1!
1)
b110001 &
#490000
0!
0)
#495000
1!
1)
b110010 &
#500000
0!
0)
#505000
1!
1)
b110011 &
#510000
0!
0)
#515000
1!
1)
b110100 &
#520000
0!
0)
#525000
1!
1)
b110101 &
#526000
b1 .
b1100100 /
b1100100 0
b1 #
0"
0*
b1 +
1$
#530000
0!
0)
#535000
1!
1)
b110110 &
#540000
0!
0)
#545000
1!
1)
b110111 &
#550000
0!
0)
#555000
1!
1)
b111000 &
#556000
1"
b0 2
b0 1
b1 -
1*
#560000
0!
0)
#565000
1!
1)
b111001 &
#566000
b1 2
b1 1
#570000
0!
0)
#575000
1!
1)
b111010 &
#576000
b10 2
b10 1
#580000
0!
0)
#585000
1!
1)
b111011 &
#586000
b11 2
b11 1
#590000
0!
0)
#595000
1!
1)
b111100 &
#596000
b100 2
b100 1
#600000
0!
0)
#605000
1!
1)
b111101 &
#606000
b101 2
b101 1
#610000
0!
0)
#615000
1!
1)
b111110 &
#616000
b110 2
b110 1
#620000
0!
0)
#625000
1!
1)
b111111 &
#626000
b111 2
b111 1
#630000
0!
0)
#635000
1!
1)
b1000000 &
#636000
b1000 2
b1000 1
#640000
0!
0)
#645000
1!
1)
b1000001 &
#646000
b1001 2
b1001 1
#650000
0!
0)
#655000
1!
1)
b1000010 &
#656000
b1010 2
b1010 1
#660000
0!
0)
#665000
1!
1)
b1000011 &
#666000
b1011 2
b1011 1
#670000
0!
0)
#675000
1!
1)
b1000100 &
#676000
b1100 2
b1100 1
#680000
0!
0)
#685000
1!
1)
b1000101 &
#686000
b1101 2
b1101 1
#690000
0!
0)
#695000
1!
1)
b1000110 &
#696000
b1110 2
b1110 1
#700000
0!
0)
#705000
1!
1)
b1000111 &
#706000
b1111 2
b1111 1
#710000
0!
0)
#715000
1!
1)
b1001000 &
#716000
b10000 2
b10000 1
#720000
0!
0)
#725000
1!
1)
b1001001 &
#726000
b10001 2
b10001 1
#730000
0!
0)
#735000
1!
1)
b1001010 &
#736000
b10010 2
b10010 1
#740000
0!
0)
#745000
1!
1)
b1001011 &
#746000
b10011 2
b10011 1
#750000
0!
0)
#755000
1!
1)
b1001100 &
#756000
b10100 2
b10100 1
#760000
0!
0)
#765000
1!
1)
b1001101 &
#766000
b10101 2
b10101 1
#770000
0!
0)
#775000
1!
1)
b1001110 &
#776000
b10110 2
b10110 1
#780000
0!
0)
#785000
1!
1)
b1001111 &
#786000
b10111 2
b10111 1
#790000
0!
0)
#795000
1!
1)
b1010000 &
#796000
b11000 2
b11000 1
#800000
0!
0)
#805000
1!
1)
b1010001 &
#806000
b11001 2
b11001 1
#810000
0!
0)
#815000
1!
1)
b1010010 &
#816000
b11010 2
b11010 1
#820000
0!
0)
#825000
1!
1)
b1010011 &
#826000
b11011 2
b11011 1
#830000
0!
0)
#835000
1!
1)
b1010100 &
#836000
b11100 2
b11100 1
#840000
0!
0)
#845000
1!
1)
b1010101 &
#846000
b11101 2
b11101 1
#850000
0!
0)
#855000
1!
1)
b1010110 &
#856000
b11110 2
b11110 1
#860000
0!
0)
#865000
1!
1)
b1010111 &
#866000
b11111 2
b11111 1
#870000
0!
0)
#875000
1!
1)
b1011000 &
#876000
b100000 2
b100000 1
#880000
0!
0)
#885000
1!
1)
b1011001 &
#886000
b100001 2
b100001 1
#890000
0!
0)
#895000
1!
1)
b1011010 &
#896000
b100010 2
b100010 1
#900000
0!
0)
#905000
1!
1)
b1011011 &
#906000
b100011 2
b100011 1
#910000
0!
0)
#915000
1!
1)
b1011100 &
#916000
b100100 2
b100100 1
#920000
0!
0)
#925000
1!
1)
b1011101 &
#926000
b100101 2
b100101 1
#930000
0!
0)
#935000
1!
1)
b1011110 &
#936000
b100110 2
b100110 1
#940000
0!
0)
#945000
1!
1)
b1011111 &
#946000
b100111 2
b100111 1
#950000
0!
0)
#955000
1!
1)
b1100000 &
#956000
b101000 2
b101000 1
#960000
0!
0)
#965000
1!
1)
b1100001 &
#966000
b101001 2
b101001 1
#970000
0!
0)
#975000
1!
1)
b1100010 &
#976000
b101010 2
b101010 1
#980000
0!
0)
#985000
1!
1)
b1100011 &
#986000
b101011 2
b101011 1
#990000
0!
0)
#995000
1!
1)
b1100100 &
#996000
b101100 2
b101100 1
#1000000
0!
0)
#1005000
1!
1)
b1100101 &
#1006000
b101101 2
b101101 1
#1010000
0!
0)
#1015000
1!
1)
b1100110 &
#1016000
b101110 2
b101110 1
#1020000
0!
0)
#1025000
1!
1)
b1100111 &
#1026000
b101111 2
b101111 1
#1030000
0!
0)
#1035000
1!
1)
b1101000 &
#1036000
b110000 2
b110000 1
#1040000
0!
0)
#1045000
1!
1)
b1101001 &
#1046000
b110001 2
b110001 1
#1050000
0!
0)
#1055000
1!
1)
b1101010 &
#1056000
b110010 2
b110010 1
#1060000
0!
0)
#1065000
1!
1)
b1101011 &
#1066000
b110011 2
b110011 1
#1070000
0!
0)
#1075000
1!
1)
b1101100 &
#1076000
b110100 2
b110100 1
#1080000
0!
0)
#1085000
1!
1)
b1101101 &
#1086000
b110101 2
b110101 1
#1090000
0!
0)
#1095000
1!
1)
b1101110 &
#1096000
b110110 2
b110110 1
#1100000
0!
0)
#1105000
1!
1)
b1101111 &
#1106000
b110111 2
b110111 1
#1110000
0!
0)
#1115000
1!
1)
b1110000 &
#1116000
b111000 2
b111000 1
#1120000
0!
0)
#1125000
1!
1)
b1110001 &
#1126000
b111001 2
b111001 1
#1130000
0!
0)
#1135000
1!
1)
b1110010 &
#1136000
b111010 2
b111010 1
#1140000
0!
0)
#1145000
1!
1)
b1110011 &
#1146000
b111011 2
b111011 1
#1150000
0!
0)
#1155000
1!
1)
b1110100 &
#1156000
b111100 2
b111100 1
#1160000
0!
0)
#1165000
1!
1)
b1110101 &
#1166000
b111101 2
b111101 1
#1170000
0!
0)
#1175000
1!
1)
b1110110 &
#1176000
b111110 2
b111110 1
#1180000
0!
0)
#1185000
1!
1)
b1110111 &
#1186000
b111111 2
b111111 1
#1190000
0!
0)
#1195000
1!
1)
b1111000 &
#1196000
b1000000 2
b1000000 1
#1200000
0!
0)
#1205000
1!
1)
b1111001 &
#1206000
b1000001 2
b1000001 1
#1210000
0!
0)
#1215000
1!
1)
b1111010 &
#1216000
b1000010 2
b1000010 1
#1220000
0!
0)
#1225000
1!
1)
b1111011 &
#1226000
b1000011 2
b1000011 1
#1230000
0!
0)
#1235000
1!
1)
b1111100 &
#1236000
b1000100 2
b1000100 1
#1240000
0!
0)
#1245000
1!
1)
b1111101 &
#1246000
b1000101 2
b1000101 1
#1250000
0!
0)
#1255000
1!
1)
b1111110 &
#1256000
b1000110 2
b1000110 1
#1260000
0!
0)
#1265000
1!
1)
b1111111 &
#1266000
b1000111 2
b1000111 1
#1270000
0!
0)
#1275000
1!
1)
b10000000 &
#1276000
b1001000 2
b1001000 1
#1280000
0!
0)
#1285000
1!
1)
b10000001 &
#1286000
b1001001 2
b1001001 1
#1290000
0!
0)
#1295000
1!
1)
b10000010 &
#1296000
b1001010 2
b1001010 1
#1300000
0!
0)
#1305000
1!
1)
b10000011 &
#1306000
b1001011 2
b1001011 1
#1310000
0!
0)
#1315000
1!
1)
b10000100 &
#1316000
b1001100 2
b1001100 1
#1320000
0!
0)
#1325000
1!
1)
b10000101 &
#1326000
b1001101 2
b1001101 1
#1330000
0!
0)
#1335000
1!
1)
b10000110 &
#1336000
b1001110 2
b1001110 1
#1340000
0!
0)
#1345000
1!
1)
b10000111 &
#1346000
b1001111 2
b1001111 1
#1350000
0!
0)
#1355000
1!
1)
b10001000 &
#1356000
b1010000 2
b1010000 1
#1360000
0!
0)
#1365000
1!
1)
b10001001 &
#1366000
b1010001 2
b1010001 1
#1370000
0!
0)
#1375000
1!
1)
b10001010 &
#1376000
b1010010 2
b1010010 1
#1380000
0!
0)
#1385000
1!
1)
b10001011 &
#1386000
b1010011 2
b1010011 1
#1390000
0!
0)
#1395000
1!
1)
b10001100 &
#1396000
b1010100 2
b1010100 1
#1400000
0!
0)
#1405000
1!
1)
b10001101 &
#1406000
b1010101 2
b1010101 1
#1410000
0!
0)
#1415000
1!
1)
b10001110 &
#1416000
b1010110 2
b1010110 1
#1420000
0!
0)
#1425000
1!
1)
b10001111 &
#1426000
b1010111 2
b1010111 1
#1430000
0!
0)
#1435000
1!
1)
b10010000 &
#1436000
b1011000 2
b1011000 1
#1440000
0!
0)
#1445000
1!
1)
b10010001 &
#1446000
b1011001 2
b1011001 1
#1450000
0!
0)
#1455000
1!
1)
b10010010 &
#1456000
b1011010 2
b1011010 1
#1460000
0!
0)
#1465000
1!
1)
b10010011 &
#1466000
b1011011 2
b1011011 1
#1470000
0!
0)
#1475000
1!
1)
b10010100 &
#1476000
b1011100 2
b1011100 1
#1480000
0!
0)
#1485000
1!
1)
b10010101 &
#1486000
b1011101 2
b1011101 1
#1490000
0!
0)
#1495000
1!
1)
b10010110 &
#1496000
b1011110 2
b1011110 1
#1500000
0!
0)
#1505000
1!
1)
b10010111 &
#1506000
b1011111 2
b1011111 1
#1510000
0!
0)
#1515000
1!
1)
b10011000 &
#1516000
b1100000 2
b1100000 1
#1520000
0!
0)
#1525000
1!
1)
b10011001 &
#1526000
b1100001 2
b1100001 1
#1530000
0!
0)
#1535000
1!
1)
b10011010 &
#1536000
b1100010 2
b1100010 1
#1540000
0!
0)
#1545000
1!
1)
b10011011 &
#1546000
b1100011 2
b1100011 1
#1550000
0!
0)
#1555000
1!
1)
b10011100 &
#1556000
b1100100 2
b1100100 1
b10 .
b110010 0
b10 #
0"
0*
b10 +
0$
#1560000
0!
0)
#1565000
1!
1)
b10011101 &
#1570000
0!
0)
#1575000
1!
1)
b10011110 &
#1580000
0!
0)
#1585000
1!
1)
b10011111 &
#1586000
1"
b0 2
b0 1
1*
#1590000
0!
0)
#1595000
1!
1)
b10100000 &
b1 ,
1$
#1596000
b1 2
b1 1
#1600000
0!
0)
#1605000
1!
1)
b10100001 &
b0 ,
0$
#1606000
b10 1
#1610000
0!
0)
#1615000
1!
1)
b10100010 &
b1 ,
1$
#1616000
b10 2
b11 1
#1620000
0!
0)
#1625000
1!
1)
b10100011 &
b0 ,
0$
#1626000
b100 1
#1630000
0!
0)
#1635000
1!
1)
b10100100 &
b1 ,
1$
#1636000
b11 2
b101 1
#1640000
0!
0)
#1645000
1!
1)
b10100101 &
b0 ,
0$
#1646000
b110 1
#1650000
0!
0)
#1655000
1!
1)
b10100110 &
b1 ,
1$
#1656000
b100 2
b111 1
#1660000
0!
0)
#1665000
1!
1)
b10100111 &
b0 ,
0$
#1666000
b1000 1
#1670000
0!
0)
#1675000
1!
1)
b10101000 &
b1 ,
1$
#1676000
b101 2
b1001 1
#1680000
0!
0)
#1685000
1!
1)
b10101001 &
b0 ,
0$
#1686000
b1010 1
#1690000
0!
0)
#1695000
1!
1)
b10101010 &
b1 ,
1$
#1696000
b110 2
b1011 1
#1700000
0!
0)
#1705000
1!
1)
b10101011 &
b0 ,
0$
#1706000
b1100 1
#1710000
0!
0)
#1715000
1!
1)
b10101100 &
b1 ,
1$
#1716000
b111 2
b1101 1
#1720000
0!
0)
#1725000
1!
1)
b10101101 &
b0 ,
0$
#1726000
b1110 1
#1730000
0!
0)
#1735000
1!
1)
b10101110 &
b1 ,
1$
#1736000
b1000 2
b1111 1
#1740000
0!
0)
#1745000
1!
1)
b10101111 &
b0 ,
0$
#1746000
b10000 1
#1750000
0!
0)
#1755000
1!
1)
b10110000 &
b1 ,
1$
#1756000
b1001 2
b10001 1
#1760000
0!
0)
#1765000
1!
1)
b10110001 &
b0 ,
0$
#1766000
b10010 1
#1770000
0!
0)
#1775000
1!
1)
b10110010 &
b1 ,
1$
#1776000
b1010 2
b10011 1
#1780000
0!
0)
#1785000
1!
1)
b10110011 &
b0 ,
0$
#1786000
b10100 1
#1790000
0!
0)
#1795000
1!
1)
b10110100 &
b1 ,
1$
#1796000
b1011 2
b10101 1
#1800000
0!
0)
#1805000
1!
1)
b10110101 &
b0 ,
0$
#1806000
b10110 1
#1810000
0!
0)
#1815000
1!
1)
b10110110 &
b1 ,
1$
#1816000
b1100 2
b10111 1
#1820000
0!
0)
#1825000
1!
1)
b10110111 &
b0 ,
0$
#1826000
b11000 1
#1830000
0!
0)
#1835000
1!
1)
b10111000 &
b1 ,
1$
#1836000
b1101 2
b11001 1
#1840000
0!
0)
#1845000
1!
1)
b10111001 &
b0 ,
0$
#1846000
b11010 1
#1850000
0!
0)
#1855000
1!
1)
b10111010 &
b1 ,
1$
#1856000
b1110 2
b11011 1
#1860000
0!
0)
#1865000
1!
1)
b10111011 &
b0 ,
0$
#1866000
b11100 1
#1870000
0!
0)
#1875000
1!
1)
b10111100 &
b1 ,
1$
#1876000
b1111 2
b11101 1
#1880000
0!
0)
#1885000
1!
1)
b10111101 &
b0 ,
0$
#1886000
b11110 1
#1890000
0!
0)
#1895000
1!
1)
b10111110 &
b1 ,
1$
#1896000
b10000 2
b11111 1
#1900000
0!
0)
#1905000
1!
1)
b10111111 &
b0 ,
0$
#1906000
b100000 1
#1910000
0!
0)
#1915000
1!
1)
b11000000 &
b1 ,
1$
#1916000
b10001 2
b100001 1
#1920000
0!
0)
#1925000
1!
1)
b11000001 &
b0 ,
0$
#1926000
b100010 1
#1930000
0!
0)
#1935000
1!
1)
b11000010 &
b1 ,
1$
#1936000
b10010 2
b100011 1
#1940000
0!
0)
#1945000
1!
1)
b11000011 &
b0 ,
0$
#1946000
b100100 1
#1950000
0!
0)
#1955000
1!
1)
b11000100 &
b1 ,
1$
#1956000
b10011 2
b100101 1
#1960000
0!
0)
#1965000
1!
1)
b11000101 &
b0 ,
0$
#1966000
b100110 1
#1970000
0!
0)
#1975000
1!
1)
b11000110 &
b1 ,
1$
#1976000
b10100 2
b100111 1
#1980000
0!
0)
#1985000
1!
1)
b11000111 &
b0 ,
0$
#1986000
b101000 1
#1990000
0!
0)
#1995000
1!
1)
b11001000 &
b1 ,
1$
#1996000
b10101 2
b101001 1
#2000000
0!
0)
#2005000
1!
1)
b11001001 &
b0 ,
0$
#2006000
b101010 1
#2010000
0!
0)
#2015000
1!
1)
b11001010 &
b1 ,
1$
#2016000
b10110 2
b101011 1
#2020000
0!
0)
#2025000
1!
1)
b11001011 &
b0 ,
0$
#2026000
b101100 1
#2030000
0!
0)
#2035000
1!
1)
b11001100 &
b1 ,
1$
#2036000
b10111 2
b101101 1
#2040000
0!
0)
#2045000
1!
1)
b11001101 &
b0 ,
0$
#2046000
b101110 1
#2050000
0!
0)
#2055000
1!
1)
b11001110 &
b1 ,
1$
#2056000
b11000 2
b101111 1
#2060000
0!
0)
#2065000
1!
1)
b11001111 &
b0 ,
0$
#2066000
b110000 1
#2070000
0!
0)
#2075000
1!
1)
b11010000 &
b1 ,
1$
#2076000
b11001 2
b110001 1
#2080000
0!
0)
#2085000
1!
1)
b11010001 &
b0 ,
0$
#2086000
b110010 1
#2090000
0!
0)
#2095000
1!
1)
b11010010 &
b1 ,
1$
#2096000
b11010 2
b110011 1
#2100000
0!
0)
#2105000
1!
1)
b11010011 &
b0 ,
0$
#2106000
b110100 1
#2110000
0!
0)
#2115000
1!
1)
b11010100 &
b1 ,
1$
#2116000
b11011 2
b110101 1
#2120000
0!
0)
#2125000
1!
1)
b11010101 &
b0 ,
0$
#2126000
b110110 1
#2130000
0!
0)
#2135000
1!
1)
b11010110 &
b1 ,
1$
#2136000
b11100 2
b110111 1
#2140000
0!
0)
#2145000
1!
1)
b11010111 &
b0 ,
0$
#2146000
b111000 1
#2150000
0!
0)
#2155000
1!
1)
b11011000 &
b1 ,
1$
#2156000
b11101 2
b111001 1
#2160000
0!
0)
#2165000
1!
1)
b11011001 &
b0 ,
0$
#2166000
b111010 1
#2170000
0!
0)
#2175000
1!
1)
b11011010 &
b1 ,
1$
#2176000
b11110 2
b111011 1
#2180000
0!
0)
#2185000
1!
1)
b11011011 &
b0 ,
0$
#2186000
b111100 1
#2190000
0!
0)
#2195000
1!
1)
b11011100 &
b1 ,
1$
#2196000
b11111 2
b111101 1
#2200000
0!
0)
#2205000
1!
1)
b11011101 &
b0 ,
0$
#2206000
b111110 1
#2210000
0!
0)
#2215000
1!
1)
b11011110 &
b1 ,
1$
#2216000
b100000 2
b111111 1
#2220000
0!
0)
#2225000
1!
1)
b11011111 &
b0 ,
0$
#2226000
b1000000 1
#2230000
0!
0)
#2235000
1!
1)
b11100000 &
b1 ,
1$
#2236000
b100001 2
b1000001 1
#2240000
0!
0)
#2245000
1!
1)
b11100001 &
b0 ,
0$
#2246000
b1000010 1
#2250000
0!
0)
#2255000
1!
1)
b11100010 &
b1 ,
1$
#2256000
b100010 2
b1000011 1
#2260000
0!
0)
#2265000
1!
1)
b11100011 &
b0 ,
0$
#2266000
b1000100 1
#2270000
0!
0)
#2275000
1!
1)
b11100100 &
b1 ,
1$
#2276000
b100011 2
b1000101 1
#2280000
0!
0)
#2285000
1!
1)
b11100101 &
b0 ,
0$
#2286000
b1000110 1
#2290000
0!
0)
#2295000
1!
1)
b11100110 &
b1 ,
1$
#2296000
b100100 2
b1000111 1
#2300000
0!
0)
#2305000
1!
1)
b11100111 &
b0 ,
0$
#2306000
b1001000 1
#2310000
0!
0)
#2315000
1!
1)
b11101000 &
b1 ,
1$
#2316000
b100101 2
b1001001 1
#2320000
0!
0)
#2325000
1!
1)
b11101001 &
b0 ,
0$
#2326000
b1001010 1
#2330000
0!
0)
#2335000
1!
1)
b11101010 &
b1 ,
1$
#2336000
b100110 2
b1001011 1
#2340000
0!
0)
#2345000
1!
1)
b11101011 &
b0 ,
0$
#2346000
b1001100 1
#2350000
0!
0)
#2355000
1!
1)
b11101100 &
b1 ,
1$
#2356000
b100111 2
b1001101 1
#2360000
0!
0)
#2365000
1!
1)
b11101101 &
b0 ,
0$
#2366000
b1001110 1
#2370000
0!
0)
#2375000
1!
1)
b11101110 &
b1 ,
1$
#2376000
b101000 2
b1001111 1
#2380000
0!
0)
#2385000
1!
1)
b11101111 &
b0 ,
0$
#2386000
b1010000 1
#2390000
0!
0)
#2395000
1!
1)
b11110000 &
b1 ,
1$
#2396000
b101001 2
b1010001 1
#2400000
0!
0)
#2405000
1!
1)
b11110001 &
b0 ,
0$
#2406000
b1010010 1
#2410000
0!
0)
