proj2_make/TOP/1_RTL/tx_fifo.v
`timescale 1ns / 1ps

module tx_fifo #(
	parameter DATA_WIDTH = 8			,
	parameter FIFO_DEPTH = 16			,
	parameter PTR_W      = $clog2(FIFO_DEPTH)	, // 4
	parameter CNT_W      = PTR_W+1		  	  // 5
)(
				clk			,
				nRst			,
				i_push			,
				i_pop			,
				i_wdata			,
				o_rdata			,
				o_empty			,
				o_full			,
				o_count
);

	input			clk			;
	input			nRst			;
	input			i_push			;
	input			i_pop			;
	input	[DATA_WIDTH-1:0]i_wdata			;
	output	[DATA_WIDTH-1:0]o_rdata			;
	output			o_empty			;
	output			o_full			;
	output	[CNT_W-1:0]	o_count			;

	wire			w_do_push		;
	wire			w_do_pop		;
	reg	[CNT_W-1:0]	r_count			;
	reg	[PTR_W-1:0]	r_wptr			;
	reg	[PTR_W-1:0]	r_rptr			;
	reg	[DATA_WIDTH-1:0]r_mem	[0:FIFO_DEPTH-1];

assign w_do_push	= i_push && !(o_full)		;
assign w_do_pop	= i_pop  && !(o_empty)			;

always @(posedge clk or negedge nRst)begin
	if (!nRst)
		r_count <= {CNT_W{1'b0}}		;
	else if (w_do_push&&!w_do_pop)
		r_count <= r_count + 1			;
	else if (!w_do_push&&w_do_pop)
		r_count <= r_count - 1			;	
end

assign o_empty = (r_count == {CNT_W{1'b0}})		;
assign o_full  = (r_count == FIFO_DEPTH)		;
assign o_count = r_count				;

always @(posedge clk or negedge nRst)begin
	if(!nRst)
		r_wptr <= {PTR_W{1'b0}}			;
	else if	(w_do_push)
		r_wptr <= r_wptr + 1			;
end

always @(posedge clk or negedge nRst)begin
	if(!nRst)
		r_rptr <= {PTR_W{1'b0}}			;
	else if (w_do_pop)
		r_rptr <= r_rptr +1			;
end

always @(posedge clk)begin
	if(w_do_push)
		r_mem[r_wptr] <= i_wdata		;

end

assign o_rdata = r_mem[r_rptr]				;

endmodule

proj2_make/TOP/2_SIM/TESTBENCH/tb_tx_fifo.v
//==============================================================================
// Testbench : th_tx_fifo
// DUT       : tx_fifo
// Method    : Self-checking. A small reference model (m_mem / m_wr / m_rd /
//             m_cnt) follows the rules written in tx_fifo.v. After every clock
//             the DUT outputs (o_count, o_empty, o_full, and o_rdata while not
//             empty) are compared with the model. Directed tests also check
//             literal expected values, so a wrong model cannot hide a bug.
//
// Tests     : (1) reset values
//             (2) fill to full, count / full flag, data order
//             (3) push when full is ignored
//             (4) full + push&pop in the same clock -> only pop is done
//             (5) drain, oldest-first order, empty flag
//             (6) pop when empty is ignored
//             (7) empty + push&pop in the same clock -> only push is done
//             (8) pointer wrap-around (push/pop alternate, and streaming)
//             (9) asynchronous reset in the middle of operation
//             (10) random push/pop (push-heavy, pop-heavy, mixed, both-heavy)
// Result    : prints PASS / FAIL per test and the number of errors at the end
//==============================================================================

`timescale 1ns / 1ps

module th_tx_fifo;

//------------------------------------------------------------------------------
// Parameters (same defaults as tx_fifo)
//------------------------------------------------------------------------------
parameter   DATA_WIDTH  = 8                         ;
parameter   FIFO_DEPTH  = 16                        ;
localparam  CNT_W       = $clog2(FIFO_DEPTH)+1      ;

//------------------------------------------------------------------------------
// DUT signals
//------------------------------------------------------------------------------
reg                     clk                         ;
reg                     nRst                        ;
reg                     i_push                      ;
reg                     i_pop                       ;
reg  [DATA_WIDTH-1:0]   i_wdata                     ;
wire [DATA_WIDTH-1:0]   o_rdata                     ;
wire                    o_empty                     ;
wire                    o_full                      ;
wire [CNT_W-1:0]        o_count                     ;

//------------------------------------------------------------------------------
// Reference model, error and coverage counters
//------------------------------------------------------------------------------
reg  [DATA_WIDTH-1:0]   m_mem   [0:FIFO_DEPTH-1]    ;   // model storage
integer                 m_wr                        ;   // model write index
integer                 m_rd                        ;   // model read index
integer                 m_cnt                       ;   // model entry count

integer                 err_cnt                     ;   // total failed checks
integer                 sec_err                     ;   // errors at test start

integer                 cov_full_push               ;   // push on full
integer                 cov_empty_pop               ;   // pop on empty
integer                 cov_full_both               ;   // push&pop on full
integer                 cov_empty_both              ;   // push&pop on empty
integer                 cov_mid_both                ;   // push&pop in the middle

integer                 seed                        ;
integer                 i                           ;
reg  [DATA_WIDTH-1:0]   pat     [0:FIFO_DEPTH-1]    ;   // hex test pattern

//------------------------------------------------------------------------------
// DUT
//------------------------------------------------------------------------------
tx_fifo #(
                .DATA_WIDTH (DATA_WIDTH )   ,
                .FIFO_DEPTH (FIFO_DEPTH )
)           uut (
                .clk        (clk        )   ,
                .nRst       (nRst       )   ,
                .i_push     (i_push     )   ,
                .i_pop      (i_pop      )   ,
                .i_wdata    (i_wdata    )   ,
                .o_rdata    (o_rdata    )   ,
                .o_empty    (o_empty    )   ,
                .o_full     (o_full     )   ,
                .o_count    (o_count    )
);

//------------------------------------------------------------------------------
// Clock : 100 MHz
//------------------------------------------------------------------------------
initial clk = 1'b0;
always  #5 clk = ~clk;

//------------------------------------------------------------------------------
// Tasks
//------------------------------------------------------------------------------
// Compare the DUT outputs with the model (called after every clock)
task compare;
begin
    if (o_count !== m_cnt) begin
        $display("[FAIL] %0t : o_count = %0d (model %0d)", $time, o_count, m_cnt);
        err_cnt = err_cnt + 1;
    end
    if (o_empty !== (m_cnt == 0)) begin
        $display("[FAIL] %0t : o_empty = %b (model %b)", $time, o_empty, (m_cnt == 0));
        err_cnt = err_cnt + 1;
    end
    if (o_full !== (m_cnt == FIFO_DEPTH)) begin
        $display("[FAIL] %0t : o_full = %b (model %b)", $time, o_full, (m_cnt == FIFO_DEPTH));
        err_cnt = err_cnt + 1;
    end
    if (m_cnt != 0 && o_rdata !== m_mem[m_rd]) begin
        $display("[FAIL] %0t : o_rdata = %h (model %h)", $time, o_rdata, m_mem[m_rd]);
        err_cnt = err_cnt + 1;
    end
end
endtask

// One clock with the given push / pop request.
//   Inputs change on the falling edge, the DUT samples them on the rising edge,
//   and the outputs are checked 1 ns after the rising edge.
task cycle(input push, input pop, input [DATA_WIDTH-1:0] data);
    reg do_push;
    reg do_pop;
begin
    @(negedge clk);
    i_push  = push;
    i_pop   = pop;
    i_wdata = data;

    // accepted requests, decided from the state before the clock edge
    do_push = push && (m_cnt != FIFO_DEPTH);
    do_pop  = pop  && (m_cnt != 0);

    // coverage : which corner cases did the test really reach
    if (push && !pop && m_cnt == FIFO_DEPTH)    cov_full_push  = cov_full_push  + 1;
    if (pop  && !push && m_cnt == 0)            cov_empty_pop  = cov_empty_pop  + 1;
    if (push && pop && m_cnt == FIFO_DEPTH)     cov_full_both  = cov_full_both  + 1;
    if (push && pop && m_cnt == 0)              cov_empty_both = cov_empty_both + 1;
    if (push && pop && m_cnt != 0 && m_cnt != FIFO_DEPTH)
                                                cov_mid_both   = cov_mid_both   + 1;

    @(posedge clk);
    #1;

    // update the model
    if (do_push) begin
        m_mem[m_wr] = data;
        m_wr        = (m_wr + 1) % FIFO_DEPTH;
        m_cnt       = m_cnt + 1;
    end
    if (do_pop) begin
        m_rd        = (m_rd + 1) % FIFO_DEPTH;
        m_cnt       = m_cnt - 1;
    end

    compare;
end
endtask

// Release both requests for n clocks
task idle(input integer n);
    integer k;
begin
    for (k = 0; k < n; k = k + 1) cycle(1'b0, 1'b0, {DATA_WIDTH{1'b0}});
end
endtask

// Literal expected values (not taken from the model)
task expect_flags(input integer e_cnt, input e_empty, input e_full);
begin
    if (o_count !== e_cnt || o_empty !== e_empty || o_full !== e_full) begin
        $display("[FAIL] %0t : count/empty/full = %0d/%b/%b (exp %0d/%b/%b)",
                  $time, o_count, o_empty, o_full, e_cnt, e_empty, e_full);
        err_cnt = err_cnt + 1;
    end
end
endtask

task expect_rdata(input [DATA_WIDTH-1:0] e_data);
begin
    if (o_rdata !== e_data) begin
        $display("[FAIL] %0t : o_rdata = %h (exp %h)", $time, o_rdata, e_data);
        err_cnt = err_cnt + 1;
    end
end
endtask

// Asynchronous reset : outputs must clear without waiting for a clock edge
task apply_reset;
begin
    i_push = 1'b0;
    i_pop  = 1'b0;
    #1 nRst = 1'b0;
    #2;
    expect_flags(0, 1'b1, 1'b0);
    m_wr  = 0;
    m_rd  = 0;
    m_cnt = 0;
    repeat (2) @(posedge clk);
    #1 nRst = 1'b1;
end
endtask

task begin_test;
begin
    sec_err = err_cnt;
end
endtask

task end_test(input [8*40-1:0] name);
begin
    if (err_cnt == sec_err) $display("[PASS] %0s", name);
    else                    $display("[FAIL] %0s", name);
end
endtask

// Random requests : p_push / p_pop are probabilities in percent
task random_phase(input integer p_push, input integer p_pop, input integer n);
    integer k;
    reg     push;
    reg     pop;
    reg [DATA_WIDTH-1:0] data;
begin
    for (k = 0; k < n; k = k + 1) begin
        push = ({$random(seed)} % 100) < p_push;
        pop  = ({$random(seed)} % 100) < p_pop;
        data = $random(seed);
        cycle(push, pop, data);
    end
end
endtask

//------------------------------------------------------------------------------
// Main sequence
//------------------------------------------------------------------------------
initial begin
    err_cnt        = 0;
    cov_full_push  = 0;
    cov_empty_pop  = 0;
    cov_full_both  = 0;
    cov_empty_both = 0;
    cov_mid_both   = 0;
    seed           = 32'h1234_5678;
    m_wr = 0;  m_rd = 0;  m_cnt = 0;

    for (i = 0; i < FIFO_DEPTH; i = i + 1)
        pat[i] = 8'hA5 + 8'h1D * i;         // distinct hex values

    nRst    = 1'b1;
    i_push  = 1'b0;
    i_pop   = 1'b0;
    i_wdata = {DATA_WIDTH{1'b0}};
    #1;

    //--------------------------------------------------------------------------
    // (1) reset values
    //--------------------------------------------------------------------------
    begin_test;
    apply_reset;
    expect_flags(0, 1'b1, 1'b0);
    end_test("(1) reset values");

    //--------------------------------------------------------------------------
    // (2) fill to full
    //--------------------------------------------------------------------------
    begin_test;
    for (i = 0; i < FIFO_DEPTH; i = i + 1) begin
        cycle(1'b1, 1'b0, pat[i]);
        expect_flags(i + 1, 1'b0, (i + 1 == FIFO_DEPTH));
        expect_rdata(pat[0]);                       // oldest entry stays at the head
    end
    end_test("(2) fill to full");

    //--------------------------------------------------------------------------
    // (3) push when full is ignored (data must not be overwritten)
    //--------------------------------------------------------------------------
    begin_test;
    cycle(1'b1, 1'b0, 8'hEE);
    cycle(1'b1, 1'b0, 8'hEF);
    expect_flags(FIFO_DEPTH, 1'b0, 1'b1);
    expect_rdata(pat[0]);
    end_test("(3) push when full ignored");

    //--------------------------------------------------------------------------
    // (4) full + push&pop in the same clock : push dropped, pop done
    //--------------------------------------------------------------------------
    begin_test;
    cycle(1'b1, 1'b1, 8'hDD);
    expect_flags(FIFO_DEPTH - 1, 1'b0, 1'b0);
    expect_rdata(pat[1]);
    end_test("(4) full + push&pop : pop only");

    //--------------------------------------------------------------------------
    // (5) refill one entry, then drain : oldest-first order, empty flag
    //--------------------------------------------------------------------------
    begin_test;
    cycle(1'b1, 1'b0, 8'h77);
    expect_flags(FIFO_DEPTH, 1'b0, 1'b1);
    for (i = 1; i < FIFO_DEPTH; i = i + 1) begin
        expect_rdata(pat[i]);
        cycle(1'b0, 1'b1, 8'h00);
        expect_flags(FIFO_DEPTH - i, 1'b0, 1'b0);
    end
    expect_rdata(8'h77);
    cycle(1'b0, 1'b1, 8'h00);
    expect_flags(0, 1'b1, 1'b0);
    end_test("(5) drain in order, empty flag");

    //--------------------------------------------------------------------------
    // (6) pop when empty is ignored
    //--------------------------------------------------------------------------
    begin_test;
    cycle(1'b0, 1'b1, 8'h00);
    cycle(1'b0, 1'b1, 8'h00);
    expect_flags(0, 1'b1, 1'b0);
    end_test("(6) pop when empty ignored");

    //--------------------------------------------------------------------------
    // (7) empty + push&pop in the same clock : pop ignored, push accepted
    //--------------------------------------------------------------------------
    begin_test;
    cycle(1'b1, 1'b1, 8'h3C);
    expect_flags(1, 1'b0, 1'b0);
    expect_rdata(8'h3C);
    cycle(1'b0, 1'b1, 8'h00);
    expect_flags(0, 1'b1, 1'b0);
    end_test("(7) empty + push&pop : push only");

    //--------------------------------------------------------------------------
    // (8) pointer wrap-around
    //--------------------------------------------------------------------------
    begin_test;
    // push, check, pop : more than 2 x FIFO_DEPTH times
    for (i = 0; i < 2 * FIFO_DEPTH + 8; i = i + 1) begin
        cycle(1'b1, 1'b0, 8'h10 + i[7:0]);
        expect_rdata(8'h10 + i[7:0]);
        cycle(1'b0, 1'b1, 8'h00);
        expect_flags(0, 1'b1, 1'b0);
    end
    // streaming : one entry stays inside, push&pop every clock
    cycle(1'b1, 1'b0, 8'hC0);
    for (i = 1; i <= 2 * FIFO_DEPTH + 8; i = i + 1) begin
        expect_rdata(8'hC0 + i[7:0] - 8'd1);        // entry pushed one clock ago
        cycle(1'b1, 1'b1, 8'hC0 + i[7:0]);
        expect_flags(1, 1'b0, 1'b0);
    end
    cycle(1'b0, 1'b1, 8'h00);
    expect_flags(0, 1'b1, 1'b0);
    end_test("(8) pointer wrap-around");

    //--------------------------------------------------------------------------
    // (9) asynchronous reset in the middle of operation
    //--------------------------------------------------------------------------
    begin_test;
    for (i = 0; i < 5; i = i + 1) cycle(1'b1, 1'b0, pat[i]);
    expect_flags(5, 1'b0, 1'b0);
    apply_reset;
    expect_flags(0, 1'b1, 1'b0);
    cycle(1'b1, 1'b0, 8'h9A);                       // pointers must start from 0 again
    expect_flags(1, 1'b0, 1'b0);
    expect_rdata(8'h9A);
    cycle(1'b0, 1'b1, 8'h00);
    expect_flags(0, 1'b1, 1'b0);
    end_test("(9) asynchronous reset");

    //--------------------------------------------------------------------------
    // (10) random requests, checked against the model every clock
    //--------------------------------------------------------------------------
    begin_test;
    random_phase(80, 20, 400);                      // push-heavy : reaches full
    random_phase(20, 80, 400);                      // pop-heavy  : reaches empty
    random_phase(50, 50, 400);                      // mixed
    random_phase(95, 95, 300);                      // push&pop together
    end_test("(10) random push/pop");

    // coverage : did the random test really reach the corner cases
    $display("[INFO] coverage : push@full=%0d pop@empty=%0d both@full=%0d both@empty=%0d both@mid=%0d",
              cov_full_push, cov_empty_pop, cov_full_both, cov_empty_both, cov_mid_both);
    if (cov_full_push == 0 || cov_empty_pop == 0 || cov_full_both == 0 ||
        cov_empty_both == 0 || cov_mid_both == 0) begin
        $display("[FAIL] a corner case was never exercised");
        err_cnt = err_cnt + 1;
    end

    //--------------------------------------------------------------------------
    if (err_cnt == 0) $display("=== th_tx_fifo : ALL PASS ===");
    else              $display("=== th_tx_fifo : FAIL (%0d errors) ===", err_cnt);
    $finish;
end

//------------------------------------------------------------------------------
// Waveform dump + watchdog
//------------------------------------------------------------------------------
initial begin
    $dumpfile("./DUMP/th_tx_fifo.vcd");
    $dumpvars(0, th_tx_fifo);
end

initial begin
    #1000000;
    $display("[FAIL] timeout");
    $finish;
end

endmodule

proj2_make/TOP/2_SIM/FUNCTION/DUMP/th_tx_fifo.vcd
$date
    Oct  9, 2026  15:35:45
$end
$version
    TOOL:	xmsim(64)	22.03-s012
$end
$timescale
    1 ps
$end

$scope module th_tx_fifo $end
$var parameter 32 !    DATA_WIDTH $end
$var parameter 32 "    FIFO_DEPTH $end
$var parameter 32 #    CNT_W $end
$var reg       1 $    clk $end
$var reg       1 %    nRst $end
$var reg       1 &    i_push $end
$var reg       1 '    i_pop $end
$var reg       8 (    i_wdata [7:0] $end
$var wire      8 )    o_rdata [7:0] $end
$var wire      1 *    o_empty  $end
$var wire      1 +    o_full  $end
$var wire      5 ,    o_count [4:0] $end
$var reg       8 -    m_mem[0] [7:0] $end
$var reg       8 .    m_mem[1] [7:0] $end
$var reg       8 /    m_mem[2] [7:0] $end
$var reg       8 0    m_mem[3] [7:0] $end
$var reg       8 1    m_mem[4] [7:0] $end
$var reg       8 2    m_mem[5] [7:0] $end
$var reg       8 3    m_mem[6] [7:0] $end
$var reg       8 4    m_mem[7] [7:0] $end
$var reg       8 5    m_mem[8] [7:0] $end
$var reg       8 6    m_mem[9] [7:0] $end
$var reg       8 7    m_mem[10] [7:0] $end
$var reg       8 8    m_mem[11] [7:0] $end
$var reg       8 9    m_mem[12] [7:0] $end
$var reg       8 :    m_mem[13] [7:0] $end
$var reg       8 ;    m_mem[14] [7:0] $end
$var reg       8 <    m_mem[15] [7:0] $end
$var integer  32 =    m_wr $end
$var integer  32 >    m_rd $end
$var integer  32 ?    m_cnt $end
$var integer  32 @    err_cnt $end
$var integer  32 A    sec_err $end
$var integer  32 B    cov_full_push $end
$var integer  32 C    cov_empty_pop $end
$var integer  32 D    cov_full_both $end
$var integer  32 E    cov_empty_both $end
$var integer  32 F    cov_mid_both $end
$var integer  32 G    seed $end
$var integer  32 H    i $end
$var reg       8 I    pat[0] [7:0] $end
$var reg       8 J    pat[1] [7:0] $end
$var reg       8 K    pat[2] [7:0] $end
$var reg       8 L    pat[3] [7:0] $end
$var reg       8 M    pat[4] [7:0] $end
$var reg       8 N    pat[5] [7:0] $end
$var reg       8 O    pat[6] [7:0] $end
$var reg       8 P    pat[7] [7:0] $end
$var reg       8 Q    pat[8] [7:0] $end
$var reg       8 R    pat[9] [7:0] $end
$var reg       8 S    pat[10] [7:0] $end
$var reg       8 T    pat[11] [7:0] $end
$var reg       8 U    pat[12] [7:0] $end
$var reg       8 V    pat[13] [7:0] $end
$var reg       8 W    pat[14] [7:0] $end
$var reg       8 X    pat[15] [7:0] $end

$scope module uut $end
$var parameter 32 Y    DATA_WIDTH $end
$var parameter 32 Z    FIFO_DEPTH $end
$var parameter 32 [    PTR_W $end
$var parameter 32 \    CNT_W $end
$var wire      1 ]    clk  $end
$var wire      1 ^    nRst  $end
$var wire      1 _    i_push  $end
$var wire      1 `    i_pop  $end
$var wire      8 a    i_wdata [7:0] $end
$var wire      8 )    o_rdata [7:0] $end
$var wire      1 *    o_empty  $end
$var wire      1 +    o_full  $end
$var wire      5 ,    o_count [4:0] $end
$var wire      1 b    w_do_push  $end
$var wire      1 c    w_do_pop  $end
$var reg       5 d    r_count [4:0] $end
$var reg       4 e    r_wptr [3:0] $end
$var reg       4 f    r_rptr [3:0] $end
$var reg       8 g    r_mem[0] [7:0] $end
$var reg       8 h    r_mem[1] [7:0] $end
$var reg       8 i    r_mem[2] [7:0] $end
$var reg       8 j    r_mem[3] [7:0] $end
$var reg       8 k    r_mem[4] [7:0] $end
$var reg       8 l    r_mem[5] [7:0] $end
$var reg       8 m    r_mem[6] [7:0] $end
$var reg       8 n    r_mem[7] [7:0] $end
$var reg       8 o    r_mem[8] [7:0] $end
$var reg       8 p    r_mem[9] [7:0] $end
$var reg       8 q    r_mem[10] [7:0] $end
$var reg       8 r    r_mem[11] [7:0] $end
$var reg       8 s    r_mem[12] [7:0] $end
$var reg       8 t    r_mem[13] [7:0] $end
$var reg       8 u    r_mem[14] [7:0] $end
$var reg       8 v    r_mem[15] [7:0] $end
$upscope $end


$scope task cycle $end
$var reg       1 w    push $end
$var reg       1 x    pop $end
$var reg       8 y    data [7:0] $end
$var reg       1 z    do_push $end
$var reg       1 {    do_pop $end
$upscope $end


$scope task idle $end
$var integer  32 |    n $end
$var integer  32 }    k $end
$upscope $end


$scope task expect_flags $end
$var integer  32 ~    e_cnt $end
$var reg       1 !!   e_empty $end
$var reg       1 "!   e_full $end
$upscope $end


$scope task expect_rdata $end
$var reg       8 #!   e_data [7:0] $end
$upscope $end


$scope task end_test $end
$var reg      320 $!   name [319:0] $end
$upscope $end


$scope task random_phase $end
$var integer  32 %!   p_push $end
$var integer  32 &!   p_pop $end
$var integer  32 '!   n $end
$var integer  32 (!   k $end
$var reg       1 )!   push $end
$var reg       1 *!   pop $end
$var reg       8 +!   data [7:0] $end
$upscope $end

$upscope $end

$enddefinitions $end
$dumpvars
b101 \
b100 [
b10000 Z
b1000 Y
b101 #
b10000 "
b1000 !
0$
1%
0&
0'
b0 (
bx )
x*
x+
bx ,
bx -
bx .
bx /
bx 0
bx 1
bx 2
bx 3
bx 4
bx 5
bx 6
bx 7
bx 8
bx 9
bx :
bx ;
bx <
b0 =
b0 >
b0 ?
b0 @
bx A
b0 B
b0 C
b0 D
b0 E
b0 F
b10010001101000101011001111000 G
b10000 H
b10100101 I
b11000010 J
b11011111 K
b11111100 L
b11001 M
b110110 N
b1010011 O
b1110000 P
b10001101 Q
b10101010 R
b11000111 S
b11100100 T
b1 U
b11110 V
b111011 W
b1011000 X
0]
1^
0_
0`
b0 a
0b
0c
bx d
bx e
bx f
bx g
bx h
bx i
bx j
bx k
bx l
bx m
bx n
bx o
bx p
bx q
bx r
bx s
bx t
bx u
bx v
xw
xx
bx y
xz
x{
bx |
bx }
bx ~
x!!
x"!
bx #!
bx $!
bx %!
bx &!
bx '!
bx (!
x)!
x*!
bx +!
$end
#1000
b0 A
#2000
0%
0^
b0 f
b0 d
b0 e
0+
1*
b0 ,
#4000
b0 ~
1!!
0"!
#5000
1$
1]
#10000
0$
0]
#15000
1$
1]
#16000
1%
b101000001100010010100100100000011100100110010101110011011001010111010000100000011101100110000101101100011101010110010101110011 $!
b0 H
1w
0x
b10100101 y
1^
#20000
0$
1&
b10100101 (
1z
0{
b10100101 a
1_
0]
1b
#25000
1$
1]
b1 d
b1 e
b10100101 g
b10100101 )
0*
b1 ,
#26000
b10100101 -
b1 =
b1 ?
b1 ~
0!!
b10100101 #!
b1 H
b11000010 y
#30000
0$
b11000010 (
b11000010 a
0]
#35000
1$
1]
b10 d
b10 e
b11000010 h
b10 ,
#36000
b11000010 .
b10 =
b10 ?
b10 ~
b10 H
b11011111 y
#40000
0$
b11011111 (
b11011111 a
0]
#45000
1$
1]
b11 d
b11 e
b11011111 i
b11 ,
#46000
b11011111 /
b11 =
b11 ?
b11 ~
b11 H
b11111100 y
#50000
0$
b11111100 (
b11111100 a
0]
#55000
1$
1]
b100 d
b100 e
b11111100 j
b100 ,
#56000
b11111100 0
b100 =
b100 ?
b100 ~
b100 H
b11001 y
#60000
0$
b11001 (
b11001 a
0]
#65000
1$
1]
b101 d
b101 e
b11001 k
b101 ,
#66000
b11001 1
b101 =
b101 ?
b101 ~
b101 H
b110110 y
#70000
0$
b110110 (
b110110 a
0]
#75000
1$
1]
b110 d
b110 e
b110110 l
b110 ,
#76000
b110110 2
b110 =
b110 ?
b110 ~
b110 H
b1010011 y
#80000
0$
b1010011 (
b1010011 a
0]
#85000
1$
1]
b111 d
b111 e
b1010011 m
b111 ,
#86000
b1010011 3
b111 =
b111 ?
b111 ~
b111 H
b1110000 y
#90000
0$
b1110000 (
b1110000 a
0]
#95000
1$
1]
b1000 d
b1000 e
b1110000 n
b1000 ,
#96000
b1110000 4
b1000 =
b1000 ?
b1000 ~
b1000 H
b10001101 y
#100000
0$
b10001101 (
b10001101 a
0]
#105000
1$
1]
b1001 d
b1001 e
b10001101 o
b1001 ,
#106000
b10001101 5
b1001 =
b1001 ?
b1001 ~
b1001 H
b10101010 y
#110000
0$
b10101010 (
b10101010 a
0]
#115000
1$
1]
b1010 d
b1010 e
b10101010 p
b1010 ,
#116000
b10101010 6
b1010 =
b1010 ?
b1010 ~
b1010 H
b11000111 y
#120000
0$
b11000111 (
b11000111 a
0]
#125000
1$
1]
b1011 d
b1011 e
b11000111 q
b1011 ,
#126000
b11000111 7
b1011 =
b1011 ?
b1011 ~
b1011 H
b11100100 y
#130000
0$
b11100100 (
b11100100 a
0]
#135000
1$
1]
b1100 d
b1100 e
b11100100 r
b1100 ,
#136000
b11100100 8
b1100 =
b1100 ?
b1100 ~
b1100 H
b1 y
#140000
0$
b1 (
b1 a
0]
#145000
1$
1]
b1101 d
b1101 e
b1 s
b1101 ,
#146000
b1 9
b1101 =
b1101 ?
b1101 ~
b1101 H
b11110 y
#150000
0$
b11110 (
b11110 a
0]
#155000
1$
1]
b1110 d
b1110 e
b11110 t
b1110 ,
#156000
b11110 :
b1110 =
b1110 ?
b1110 ~
b1110 H
b111011 y
#160000
0$
b111011 (
b111011 a
0]
#165000
1$
1]
b1111 d
b1111 e
b111011 u
b1111 ,
#166000
b111011 ;
b1111 =
b1111 ?
b1111 ~
b1111 H
b1011000 y
#170000
0$
b1011000 (
b1011000 a
0]
#175000
1$
1]
b10000 d
b0 e
b1011000 v
1+
b10000 ,
0b
#176000
b1011000 <
b0 =
b10000 ?
b10000 ~
1"!
b10000 H
b101000001100100010100100100000011001100110100101101100011011000010000001110100011011110010000001100110011101010110110001101100 $!
b11101110 y
#180000
0$
b11101110 (
0z
b1 B
b11101110 a
0]
#185000
1$
1]
#186000
b11101111 y
#190000
0$
b11101111 (
b10 B
b11101111 a
0]
#195000
1$
1]
#196000
b10100000110011001010010010000001110000011101010111001101101000001000000111011101101000011001010110111000100000011001100111010101101100011011000010000001101001011001110110111001101111011100100110010101100100 $!
1x
b11011101 y
#200000
0$
1'
b11011101 (
1{
b1 D
b11011101 a
1`
0]
1c
#205000
1$
1]
b1 f
b1111 d
0+
b11000010 )
b1111 ,
1b
#206000
b1 >
b1111 ?
b1111 ~
0"!
b11000010 #!
b1010000011010000101001001000000110011001110101011011000110110000100000001010110010000001110000011101010111001101101000001001100111000001101111011100000010000000111010001000000111000001101111011100000010000001101111011011100110110001111001 $!
0x
b1110111 y
#210000
0$
0'
b1110111 (
1z
0{
b1110111 a
0`
0]
0c
#215000
1$
1]
b10000 d
b1 e
b1110111 g
1+
b10000 ,
0b
#216000
b1110111 -
b1 =
b10000 ?
b10000 ~
1"!
b1 H
0w
1x
b0 y
#220000
0$
0&
1'
b0 (
0z
1{
b0 a
1`
0_
0]
1c
#225000
1$
1]
b10 f
b1111 d
0+
b11011111 )
b1111 ,
#226000
b10 >
b1111 ?
b1111 ~
0"!
b10 H
b11011111 #!
#230000
0$
0]
#235000
1$
1]
b11 f
b1110 d
b11111100 )
b1110 ,
#236000
b11 >
b1110 ?
b1110 ~
b11 H
b11111100 #!
#240000
0$
0]
#245000
1$
1]
b100 f
b1101 d
b11001 )
b1101 ,
#246000
b100 >
b1101 ?
b1101 ~
b100 H
b11001 #!
#250000
0$
0]
#255000
1$
1]
b101 f
b1100 d
b110110 )
b1100 ,
#256000
b101 >
b1100 ?
b1100 ~
b101 H
b110110 #!
#260000
0$
0]
#265000
1$
1]
b110 f
b1011 d
b1010011 )
b1011 ,
#266000
b110 >
b1011 ?
b1011 ~
b110 H
b1010011 #!
#270000
0$
0]
#275000
1$
1]
b111 f
b1010 d
b1110000 )
b1010 ,
#276000
b111 >
b1010 ?
b1010 ~
b111 H
b1110000 #!
#280000
0$
0]
#285000
1$
1]
b1000 f
b1001 d
b10001101 )
b1001 ,
#286000
b1000 >
b1001 ?
b1001 ~
b1000 H
b10001101 #!
#290000
0$
0]
#295000
1$
1]
b1001 f
b1000 d
b10101010 )
b1000 ,
#296000
b1001 >
b1000 ?
b1000 ~
b1001 H
b10101010 #!
#300000
0$
0]
#305000
1$
1]
b1010 f
b111 d
b11000111 )
b111 ,
#306000
b1010 >
b111 ?
b111 ~
b1010 H
b11000111 #!
#310000
0$
0]
#315000
1$
1]
b1011 f
b110 d
b11100100 )
b110 ,
#316000
b1011 >
b110 ?
b110 ~
b1011 H
b11100100 #!
#320000
0$
0]
#325000
1$
1]
b1100 f
b101 d
b1 )
b101 ,
#326000
b1100 >
b101 ?
b101 ~
b1100 H
b1 #!
#330000
0$
0]
#335000
1$
1]
b1101 f
b100 d
b11110 )
b100 ,
#336000
b1101 >
b100 ?
b100 ~
b1101 H
b11110 #!
#340000
0$
0]
#345000
1$
1]
b1110 f
b11 d
b111011 )
b11 ,
#346000
b1110 >
b11 ?
b11 ~
b1110 H
b111011 #!
#350000
0$
0]
#355000
1$
1]
b1111 f
b10 d
b1011000 )
b10 ,
#356000
b1111 >
b10 ?
b10 ~
b1111 H
b1011000 #!
#360000
0$
0]
#365000
1$
1]
b0 f
b1 d
b1110111 )
b1 ,
#366000
b0 >
b1 ?
b1 ~
b10000 H
b1110111 #!
#370000
0$
0]
#375000
1$
1]
b1 f
b0 d
1*
b11000010 )
b0 ,
0c
#376000
b1 >
b0 ?
b0 ~
1!!
b1010000011010100101001001000000110010001110010011000010110100101101110001000000110100101101110001000000110111101110010011001000110010101110010001011000010000001100101011011010111000001110100011110010010000001100110011011000110000101100111 $!
#380000
0$
0{
b1 C
0]
#385000
1$
1]
#390000
0$
b10 C
0]
#395000
1$
1]
#396000
b10100000110110001010010010000001110000011011110111000000100000011101110110100001100101011011100010000001100101011011010111000001110100011110010010000001101001011001110110111001101111011100100110010101100100 $!
1w
b111100 y
#400000
0$
1&
b111100 (
1z
b1 E
b111100 a
1_
0]
1b
#405000
1$
1]
b1 d
b10 e
b111100 h
b111100 )
0*
b1 ,
1c
#406000
b111100 .
b10 =
b1 ?
b1 ~
0!!
b111100 #!
0w
b0 y
#410000
0$
0&
b0 (
0z
1{
b0 a
0_
0]
0b
#415000
1$
1]
b10 f
b0 d
1*
b11011111 )
b0 ,
0c
#416000
b10 >
b0 ?
b0 ~
1!!
b10100000110111001010010010000001100101011011010111000001110100011110010010000000101011001000000111000001110101011100110110100000100110011100000110111101110000001000000011101000100000011100000111010101110011011010000010000001101111011011100110110001111001 $!
b0 H
1w
0x
b10000 y
#420000
0$
1&
0'
b10000 (
1z
0{
b10000 a
0`
1_
0]
1b
#425000
1$
1]
b1 d
b11 e
b10000 i
b10000 )
0*
b1 ,
#426000
b10000 /
b11 =
b1 ?
b10000 #!
0w
1x
b0 y
#430000
0$
0&
1'
b0 (
0z
1{
b0 a
1`
0_
0]
0b
1c
#435000
1$
1]
b11 f
b0 d
1*
b11111100 )
b0 ,
0c
#436000
b11 >
b0 ?
b1 H
1w
0x
b10001 y
#440000
0$
1&
0'
b10001 (
1z
0{
b10001 a
0`
1_
0]
1b
#445000
1$
1]
b1 d
b100 e
b10001 j
b10001 )
0*
b1 ,
#446000
b10001 0
b100 =
b1 ?
b10001 #!
0w
1x
b0 y
#450000
0$
0&
1'
b0 (
0z
1{
b0 a
1`
0_
0]
0b
1c
